johann/__init__.py
johann/api_conductor.py
johann/celeryconfig.py
johann/conductor_app.py
johann/conductor_tasks.py
johann/docker_host_control.py
johann/host.py
johann/host_control.py
johann/host_control_util.py
johann/johann_main.py
johann/measure.py
johann/player.py
johann/score.py
johann/tasks_main.py
johann/tasks_util.py
johann/util.py
johann/scores/test_johann_pushing.yml
johann/shared/__init__.py
johann/shared/config.py
johann/shared/enums.py
johann/shared/errors.py
johann/shared/fields.py
johann/shared/logger.py
johann-0.3.0a0.dist-info/AUTHORS
johann-0.3.0a0.dist-info/LICENSE
johann-0.3.0a0.dist-info/METADATA
johann-0.3.0a0.dist-info/WHEEL
johann-0.3.0a0.dist-info/top_level.txt
johann-0.3.0a0.dist-info/RECORD
