Metadata-Version: 2.1
Name: johann
Version: 0.3.0a0
Summary: Johann, the lightweight and flexible scenario orchestrator
Home-page: https://github.com/johannsdg/johann
Author: Jeffrey James
Author-email: lobotmcj@gmail.com
License: BSD-3-Clause
Platform: UNKNOWN
Classifier: Development Status :: 3 - Alpha
Classifier: License :: OSI Approved :: BSD License
Classifier: Programming Language :: Python :: 3
Classifier: Programming Language :: Python :: 3 :: Only
Classifier: Operating System :: POSIX :: Linux
Requires-Python: >=3.6, <4
Requires-Dist: aiohttp (<4.0,>=3.6)
Requires-Dist: celery (==4.4.6)
Requires-Dist: dataclasses (<0.7)
Requires-Dist: docker (<5.0,>=4.1)
Requires-Dist: fastapi (<1.0,>=0.56.0)
Requires-Dist: logzero (<2.0,>=1.5)
Requires-Dist: marshmallow (<4.0,>=3.2)
Requires-Dist: marshmallow-enum (<2.0,>=1.5.0)
Requires-Dist: natsort (<7.0,>=6.0.0)
Requires-Dist: psutil (<6.0,>=5.6)
Requires-Dist: python-dotenv (<0.11.0,>=0.10.1)
Requires-Dist: redis (<4.0,>=3.2)
Requires-Dist: requests (<3.0,>=2.24.0)
Requires-Dist: ruamel.yaml (<0.16,>0.15.0)
